{"stat.useItem.minecraft.bow":1734,"stat.useItem.minecraft.lapis_block":1,"stat.useItem.minecraft.repeater":71,"stat.leaveGame":59,"stat.mineBlock.minecraft.cobblestone":1,"stat.useItem.minecraft.beacon":2,"stat.entityKilledBy.Witch":1,"stat.useItem.minecraft.soul_sand":17,"stat.useItem.minecraft.diamond_sword":279,"stat.useItem.minecraft.glowstone":305,"stat.breakItem.minecraft.wooden_sword":1,"stat.swimOneCm":25353,"stat.useItem.minecraft.snow":28,"stat.useItem.minecraft.planks":206,"stat.climbOneCm":7136,"stat.useItem.minecraft.golden_shovel":33,"stat.useItem.minecraft.redstone_torch":22,"stat.useItem.minecraft.obsidian":47,"stat.useItem.minecraft.dirt":174,"achievement.exploreAllBiomes":{"value":0,"progress":["Savanna Plateau","Roofed Forest","Plains","The End","Beach","DesertHills","Forest","River","Ocean","Taiga","Desert","Extreme Hills","Savanna"]},"stat.useItem.minecraft.activator_rail":1,"stat.useItem.minecraft.detector_rail":2,"stat.useItem.minecraft.rail":1,"stat.useItem.minecraft.anvil":2,"stat.flyOneCm":3634281,"stat.useItem.minecraft.ender_pearl":8,"stat.killEntity.Witch":22,"stat.useItem.minecraft.cooked_beef":4,"stat.mineBlock.minecraft.iron_ore":1,"stat.timeSinceDeath":12686,"stat.hopperInspected":12,"stat.useItem.minecraft.sign":12,"stat.useItem.minecraft.lever":2,"stat.mineBlock.minecraft.coal_ore":20,"stat.killEntity.Creeper":2,"stat.useItem.minecraft.minecart":18,"stat.useItem.minecraft.redstone":203,"stat.useItem.minecraft.milk_bucket":11,"achievement.mineWood":10,"stat.sprintOneCm":429518,"stat.useItem.minecraft.diamond_block":18,"stat.useItem.minecraft.diamond_shovel":3232,"stat.useItem.minecraft.stone_stairs":10,"stat.useItem.minecraft.stone_slab":5,"stat.useItem.minecraft.bed":1,"achievement.openInventory":335,"stat.useItem.minecraft.snowball":422,"stat.mineBlock.minecraft.diamond_ore":4,"stat.useItem.minecraft.flint_and_steel":2,"stat.useItem.minecraft.wooden_button":14,"stat.useItem.minecraft.stone_pressure_plate":16,"stat.useItem.minecraft.diamond_pickaxe":880,"stat.useItem.minecraft.dye":12,"stat.breakItem.minecraft.diamond_boots":2,"stat.breakItem.minecraft.golden_shovel":1,"stat.deaths":190,"stat.drop":35,"stat.playOneMinute":1210964,"stat.useItem.minecraft.wooden_sword":77,"stat.killEntity.Zombie":12,"stat.mineBlock.minecraft.gold_ore":2,"stat.mineBlock.minecraft.tallgrass":4,"stat.diveOneCm":29593,"stat.chestOpened":9,"stat.useItem.minecraft.sticky_piston":21,"stat.useItem.minecraft.stone":187,"stat.useItem.minecraft.sponge":1,"stat.killEntity.Slime":19,"stat.useItem.minecraft.diamond_axe":21,"stat.useItem.minecraft.waterlily":21,"stat.useItem.minecraft.apple":1,"stat.useItem.minecraft.carpet":271,"stat.useItem.minecraft.bedrock":5,"stat.jump":3916,"stat.useItem.minecraft.sand":1,"stat.breakItem.minecraft.leather_helmet":1,"stat.fallOneCm":328428,"stat.crouchOneCm":875218,"stat.breakItem.minecraft.leather_chestplate":1,"stat.useItem.minecraft.stone_button":5,"stat.useItem.minecraft.dispenser":3,"stat.useItem.minecraft.glass":271,"stat.useItem.minecraft.sapling":2,"stat.mineBlock.minecraft.log2":4,"stat.damageTaken":62231,"stat.dispenserInspected":8,"stat.breakItem.minecraft.leather_boots":1,"stat.killEntity.CaveSpider":8,"stat.mineBlock.minecraft.snow":3148,"stat.mineBlock.minecraft.gravel":1,"stat.mineBlock.minecraft.glass":1,"stat.useItem.minecraft.stone_sword":27,"stat.damageDealt":290625,"stat.useItem.minecraft.wool":2,"stat.killEntity.Cow":22,"stat.mineBlock.minecraft.dirt":72,"stat.useItem.minecraft.command_block":91,"stat.walkOneCm":2869364,"stat.playerKills":120,"stat.useItem.minecraft.chest":1,"stat.useItem.minecraft.comparator":1,"stat.useItem.minecraft.cobblestone":86,"stat.killEntity.LavaSlime":1,"stat.minecartOneCm":99260,"stat.useItem.minecraft.redstone_block":8,"stat.useItem.minecraft.stained_hardened_clay":454,"stat.useItem.minecraft.barrier":114,"stat.mobKills":89,"stat.useItem.minecraft.wooden_pressure_plate":5,"stat.useItem.minecraft.stonebrick":204,"stat.mineBlock.minecraft.log":9,"stat.breakItem.minecraft.diamond_shovel":1,"stat.mineBlock.minecraft.leaves":15,"stat.mineBlock.minecraft.redstone_ore":7,"stat.useItem.minecraft.wooden_axe":16,"stat.breakItem.minecraft.leather_leggings":1,"stat.mineBlock.minecraft.stone":842}